setup.py
zorch/__init__.py
zorch/postprocess.py
zorch/preprocess.py
zorch/tools.py
zorch.egg-info/PKG-INFO
zorch.egg-info/SOURCES.txt
zorch.egg-info/dependency_links.txt
zorch.egg-info/top_level.txt